<?xml version="1.0" encoding="UTF-8"?>
<objects serializationModel="Studio.02.02.00">
	<object class="ParameterPreset" id="{f957feb3-c749-4d19-b0e1-ecc815762be7}">
		<property name="name">
			<value>isReeling</value>
		</property>
		<relationship name="folder">
			<destination>{f3734e9e-ea27-4ae3-ad06-6b8cca693694}</destination>
		</relationship>
		<relationship name="parameter">
			<destination>{68824268-19a6-4882-b1c4-1bc0aa06caec}</destination>
		</relationship>
	</object>
	<object class="GameParameter" id="{68824268-19a6-4882-b1c4-1bc0aa06caec}">
		<property name="parameterType">
			<value>2</value>
		</property>
		<property name="maximum">
			<value>2</value>
		</property>
		<property name="enumerationLabels">
			<value>No</value>
			<value>Yes</value>
		</property>
		<property name="initialValue">
			<value>0</value>
		</property>
	</object>
</objects>
