<?xml version="1.0" encoding="UTF-8"?>
<objects serializationModel="Studio.02.02.00">
	<object class="AudioFile" id="{d8c293ce-2817-47d9-b16f-84ebb5f40fd9}">
		<property name="assetPath">
			<value>buzz-006.wav</value>
		</property>
		<property name="frequencyInKHz">
			<value>44.0999985</value>
		</property>
		<property name="channelCount">
			<value>2</value>
		</property>
		<property name="length">
			<value>5.4559863945578231</value>
		</property>
		<relationship name="masterAssetFolder">
			<destination>{f97b6810-5b32-49c9-b34b-e70f6e53efe1}</destination>
		</relationship>
	</object>
</objects>
